FaceReco/FaceReco.py
FaceReco/__init__.py
FaceReco/dlib_face_recognition_resnet_model_v1.dat
FaceReco/opencv_face_detector.pbtxt
FaceReco/opencv_face_detector_uint8.pb
FaceReco/shape_predictor_68_face_landmarks.dat
FaceReco/supportFiles.py
FaceReco-0.1.0.dist-info/METADATA
FaceReco-0.1.0.dist-info/WHEEL
FaceReco-0.1.0.dist-info/top_level.txt
FaceReco-0.1.0.dist-info/RECORD
