Metadata-Version: 2.1
Name: FaceReco
Version: 0.1.0
Summary: Face Recognition package in python
Home-page: https://github.com/1297rohit/FaceReco
Author: 1297rohit
Author-email: 1297rohit@gmail.com
License: MIT license
Keywords: face_recognition
Platform: UNKNOWN
Classifier: Programming Language :: Python :: 3
Classifier: License :: OSI Approved :: MIT License
Classifier: Operating System :: OS Independent
Requires-Dist: dlib
Requires-Dist: opencv-python
Requires-Dist: numpy
Requires-Dist: imutils
Requires-Dist: tqdm
